[{"id":78643,"name":"Airdrie Gartlea Rd","key":"L-AHWQ02","type":"LEAF","parent":{"id":78001},"area":3125.9,"summer_temp":15.5,"winter_temp":15.5,"activity":"DEPARTMENT-STORE-FOOD","reference_devices":[{"device":{"id":433498},"type":"MAINSUPPLY"},{"device":{"id":424991},"type":"GAS"}],"address":{"street":"Gartlea Rd","zip":"ML6 9LH","city":"Airdrie","country":{"name":"United Kingdom","code":"GB"},"coordinates":{"latitude":55.86123,"longitude":-3.973576}},"optimisedDate":"2018-10-16"},{"id":78644,"name":"Aldershot","key":"L-UJANPH","type":"LEAF","parent":{"id":77903},"area":3990.09,"summer_temp":15.5,"winter_temp":15.5,"activity":"DEPARTMENT-STORE-FOOD","reference_devices":[],"address":{"street":"Alexandra Road","zip":"GU11 3PP","city":"Aldershot","country":{"name":"United Kingdom","code":"GB"},"coordinates":{"latitude":51.24859,"longitude":-0.775382}}},{"id":78645,"name":"Aldridge Anchor Rd","key":"L-9FWIXW","type":"LEAF","parent":{"id":78000},"area":2474.1,"summer_temp":15.5,"winter_temp":15.5,"activity":"DEPARTMENT-STORE-FOOD","reference_devices":[{"device":{"id":433305},"type":"MAINSUPPLY"},{"device":{"id":424999},"type":"GAS"}],"address":{"street":"Anchor Road","zip":"WS9 8PT","city":"Aldridge","country":{"name":"United Kingdom","code":"GB"},"coordinates":{"latitude":52.604084,"longitude":-1.918517}},"optimisedDate":"2018-11-09"},{"id":78646,"name":"Alloa Clackmannan Rd","key":"L-PRBKCK","type":"LEAF","parent":{"id":78001},"area":2125.62,"summer_temp":15.5,"winter_temp":15.5,"activity":"DEPARTMENT-STORE-FOOD","reference_devices":[{"device":{"id":433535},"type":"MAINSUPPLY"},{"device":{"id":434097},"type":"OUTDOORTEMP"}],"address":{"street":"Clackmannan Road","zip":"FK10 1RR","city":"Alloa","country":{"name":"United Kingdom","code":"GB"},"coordinates":{"latitude":56.116016,"longitude":-3.779297}},"optimisedDate":"2018-10-15"},{"id":78647,"name":"Alness","key":"L-HE9OTH","type":"LEAF","parent":{"id":78001},"area":1553.9,"summer_temp":15.5,"winter_temp":15.5,"activity":"DEPARTMENT-STORE-FOOD","reference_devices":[{"device":{"id":433460},"type":"MAINSUPPLY"},{"device":{"id":424977},"type":"GAS"},{"device":{"id":434098},"type":"OUTDOORTEMP"}],"address":{"street":"Dalmore Road","zip":"IV17 0UY","city":"Alness","country":{"name":"United Kingdom","code":"GB"},"coordinates":{"latitude":57.69354,"longitude":-4.251224}},"optimisedDate":"2018-10-16"},{"id":78648,"name":"Alnwick - Fenkle Street","key":"L-OS6EKS","type":"LEAF","parent":{"id":78001},"area":1383.98,"summer_temp":15.5,"winter_temp":15.5,"activity":"DEPARTMENT-STORE-FOOD","reference_devices":[],"address":{"street":"Fenkle Street","zip":"NE66 1HW","city":"Alnwick","country":{"name":"United Kingdom","code":"GB"},"coordinates":{"latitude":55.413616,"longitude":-1.707788}}},{"id":78649,"name":"Arbroath Hume St","key":"L-FKIEGA","type":"LEAF","parent":{"id":78001},"area":2086.6,"summer_temp":15.5,"winter_temp":15.5,"activity":"DEPARTMENT-STORE-FOOD","reference_devices":[{"device":{"id":434102},"type":"OUTDOORTEMP"},{"device":{"id":424975},"type":"GAS"},{"device":{"id":433480},"type":"MAINSUPPLY"}],"address":{"street":"Hume Street","zip":"DD11 1UH","city":"Arbroath","country":{"name":"United Kingdom","code":"GB"},"coordinates":{"latitude":56.5614,"longitude":-2.587146}},"optimisedDate":"2018-10-17"},{"id":78650,"name":"Armthorpe","key":"L-CR7QNP","type":"LEAF","parent":{"id":78001},"area":679.96,"summer_temp":15.5,"winter_temp":15.5,"activity":"DEPARTMENT-STORE-FOOD","reference_devices":[],"address":{"street":"Church Street","zip":"DN3 3AE","city":"Armthorpe","country":{"name":"United Kingdom","code":"GB"},"coordinates":{"latitude":53.535625,"longitude":-1.056638}}},{"id":78652,"name":"Aylesbury Station Way","key":"L-YRYCJI","type":"LEAF","parent":{"id":77908},"area":2965.93,"summer_temp":15.5,"winter_temp":15.5,"activity":"DEPARTMENT-STORE-FOOD","reference_devices":[{"device":{"id":437878},"type":"OUTDOORTEMP"},{"device":{"id":433128},"type":"MAINSUPPLY"},{"device":{"id":424917},"type":"GAS"}],"address":{"street":"Station Way","zip":"HP20 2HX","city":"HP20 2HX","country":{"name":"United Kingdom","code":"GB"},"coordinates":{"latitude":51.81439,"longitude":-0.816628}},"optimisedDate":"2018-09-28"},{"id":78653,"name":"Ayr Castlehill Rd","key":"L-M3JWHH","type":"LEAF","parent":{"id":78001},"area":2475.22,"summer_temp":15.5,"winter_temp":15.5,"activity":"DEPARTMENT-STORE-FOOD","reference_devices":[{"device":{"id":433497},"type":"MAINSUPPLY"},{"device":{"id":424962},"type":"GAS"},{"device":{"id":433848},"type":"OUTDOORTEMP"}],"address":{"street":"Castlehill Road","zip":"KA7 2JB","city":"Ayr","country":{"name":"United Kingdom","code":"GB"},"coordinates":{"latitude":55.45249,"longitude":-4.622056}},"optimisedDate":"2018-10-10"},{"id":78654,"name":"Bacup","key":"L-OSO28B","type":"LEAF","parent":{"id":78001},"area":1179.3,"summer_temp":15.5,"winter_temp":15.5,"activity":"DEPARTMENT-STORE-FOOD","reference_devices":[],"address":{"street":"Market Street/Lee Street/Henrietta Street","zip":"OL13","city":"Bacup, Lancashire","country":{"name":"United Kingdom","code":"GB"},"coordinates":{"latitude":53.70138,"longitude":-2.201009}}},{"id":78655,"name":"Balby, Doncaster","key":"L-IN8PR3","type":"LEAF","parent":{"id":78001},"area":3784.78,"summer_temp":15.5,"winter_temp":15.5,"activity":"DEPARTMENT-STORE-FOOD","reference_devices":[],"address":{"street":"First Point Business Park, Woodfield Way","zip":"DN4 5JP","city":"Balby, Doncaster","country":{"name":"United Kingdom","code":"GB"},"coordinates":{"latitude":53.49956,"longitude":-1.125708}}},{"id":78656,"name":"Bamber Bridge Preston","key":"L-FXHUGD","type":"LEAF","parent":{"id":78001},"area":1203.9,"summer_temp":15.5,"winter_temp":15.5,"activity":"DEPARTMENT-STORE-FOOD","reference_devices":[{"device":{"id":424915},"type":"GAS"},{"device":{"id":433409},"type":"MAINSUPPLY"},{"device":{"id":434109},"type":"OUTDOORTEMP"}],"address":{"street":"Station Rd","zip":"PR5 6QR","city":"Bamber Bridge","country":{"name":"United Kingdom","code":"GB"},"coordinates":{"latitude":53.734882,"longitude":-2.662826}},"optimisedDate":"2018-11-02"},{"id":78657,"name":"Banbury Swan Close","key":"L-VH9JDM","type":"LEAF","parent":{"id":78000},"area":3150.34,"summer_temp":15.5,"winter_temp":15.5,"activity":"DEPARTMENT-STORE-FOOD","reference_devices":[{"device":{"id":424967},"type":"GAS"},{"device":{"id":434111},"type":"OUTDOORTEMP"},{"device":{"id":433328},"type":"MAINSUPPLY"}],"address":{"street":"Swan Close Road","zip":"OX16","city":"Banbury","country":{"name":"United Kingdom","code":"GB"},"coordinates":{"latitude":52.057556,"longitude":-1.331441}},"optimisedDate":"2018-09-21"},{"id":78658,"name":"Banchory North Deeside Rd","key":"L-DMZFRN","type":"LEAF","parent":{"id":78001},"area":1090.4,"summer_temp":15.5,"winter_temp":15.5,"activity":"DEPARTMENT-STORE-FOOD","reference_devices":[{"device":{"id":434110},"type":"OUTDOORTEMP"},{"device":{"id":425389},"type":"GAS"},{"device":{"id":473099},"type":"MAINSUPPLY"}],"address":{"street":"North Deeside Road","zip":"AB31 5YR","city":"Banchory","country":{"name":"United Kingdom","code":"GB"},"coordinates":{"latitude":57.054897,"longitude":-2.479514}},"optimisedDate":"2018-10-18"},{"id":78659,"name":"Bangor Holyhead Rd","key":"L-LSCT7C","type":"LEAF","parent":{"id":78000},"area":1999,"summer_temp":15.5,"winter_temp":15.5,"activity":"DEPARTMENT-STORE-FOOD","reference_devices":[{"device":{"id":434112},"type":"OUTDOORTEMP"},{"device":{"id":433263},"type":"MAINSUPPLY"},{"device":{"id":424928},"type":"GAS"}],"address":{"street":"Holyhead Road","zip":"LL57 2EE","city":"Bangor","country":{"name":"United Kingdom","code":"GB"},"coordinates":{"latitude":53.22562,"longitude":-4.135065}},"optimisedDate":"2018-10-11"},{"id":78660,"name":"Bargoed","key":"L-QZEW4B","type":"LEAF","parent":{"id":78000},"area":2696.33,"summer_temp":15.5,"winter_temp":15.5,"activity":"DEPARTMENT-STORE-FOOD","reference_devices":[],"address":{"street":"Cardiff Road","zip":"CF81","city":"Bargoed","country":{"name":"United Kingdom","code":"GB"},"coordinates":{"latitude":51.683453,"longitude":-3.229254}}},{"id":78661,"name":"Barnard Castle Galgate","key":"L-Q4I1X4","type":"LEAF","parent":{"id":78001},"area":1263.39,"summer_temp":15.5,"winter_temp":15.5,"activity":"DEPARTMENT-STORE-FOOD","reference_devices":[],"address":{"street":"Galgate, 23","zip":"DL12 8EQ","city":"Barnard Castle","country":{"name":"United Kingdom","code":"GB"},"coordinates":{"latitude":54.544647,"longitude":-1.92338}}},{"id":78662,"name":"Barnsley Brampton","key":"L-W8ZR3G","type":"LEAF","parent":{"id":78001},"area":3757.28,"summer_temp":15.5,"winter_temp":15.5,"activity":"DEPARTMENT-STORE-FOOD","reference_devices":[],"address":{"street":"Corton Wood","zip":"S73 0TB","city":"Brampton","country":{"name":"United Kingdom","code":"GB"},"coordinates":{"latitude":53.50899,"longitude":-1.389124}}},{"id":78663,"name":"Barnsley Westway","key":"L-276WOG","type":"LEAF","parent":{"id":78001},"area":3564.78,"summer_temp":15.5,"winter_temp":15.5,"activity":"DEPARTMENT-STORE-FOOD","reference_devices":[],"address":{"street":"Lower Thomas Street","zip":"S70 1LQ","city":"Off West Way","country":{"name":"United Kingdom","code":"GB"},"coordinates":{"latitude":53.549168,"longitude":-1.481121}},"optimisedDate":"2018-12-03"},{"id":78664,"name":"Barrack Street Glasgow","key":"L-OEEXFG","type":"LEAF","parent":{"id":78001},"area":2254,"summer_temp":15.5,"winter_temp":15.5,"activity":"DEPARTMENT-STORE-FOOD","reference_devices":[{"device":{"id":433751},"type":"MAINSUPPLY"},{"device":{"id":425073},"type":"GAS"},{"device":{"id":433839},"type":"OUTDOORTEMP"}],"address":{"street":"Gallowgate","zip":"G4 0TZ","city":"Glasgow","country":{"name":"United Kingdom","code":"GB"},"coordinates":{"latitude":55.854553,"longitude":-4.220517}},"optimisedDate":"2018-10-16"},{"id":78665,"name":"Barrow Strand","key":"L-I0IQ1F","type":"LEAF","parent":{"id":78001},"area":3675.99,"summer_temp":15.5,"winter_temp":15.5,"activity":"DEPARTMENT-STORE-FOOD","reference_devices":[],"address":{"street":"Strand","zip":"LA14 2HQ","city":"Barrow In Furness","country":{"name":"United Kingdom","code":"GB"},"coordinates":{"latitude":54.109043,"longitude":-3.223882}}},{"id":78666,"name":"Barry Heol Ceiniog","key":"L-IFMIZS","type":"LEAF","parent":{"id":77903},"area":3349.34,"summer_temp":15.5,"winter_temp":15.5,"activity":"DEPARTMENT-STORE-FOOD","reference_devices":[{"device":{"id":433621},"type":"MAINSUPPLY"},{"device":{"id":434117},"type":"OUTDOORTEMP"},{"device":{"id":424979},"type":"GAS"}],"address":{"street":"Heol Ceiniog","zip":"CF63 4BA","city":"Barry","country":{"name":"United Kingdom","code":"GB"},"coordinates":{"latitude":51.401627,"longitude":-3.270886}},"optimisedDate":"2018-10-06"},{"id":78667,"name":"Basingstoke Thorneycroft","key":"L-AAQ32K","type":"LEAF","parent":{"id":77903},"area":3487.12,"summer_temp":15.5,"winter_temp":15.5,"activity":"DEPARTMENT-STORE-FOOD","reference_devices":[],"address":{"street":"Worting Road","zip":"RG21 8BJ","city":"Basingstoke","country":{"name":"United Kingdom","code":"GB"},"coordinates":{"latitude":51.262463,"longitude":-1.105179}}},{"id":78669,"name":"Bathgate","key":"L-FXNUDI","type":"LEAF","parent":{"id":78001},"area":3018.14,"summer_temp":15.5,"winter_temp":15.5,"activity":"DEPARTMENT-STORE-FOOD","reference_devices":[{"device":{"id":434120},"type":"OUTDOORTEMP"},{"device":{"id":433557},"type":"MAINSUPPLY"}],"address":{"street":"Linkston Way, 2","zip":"EH48 2SS","city":"Bathgate, West Lothian","country":{"name":"United Kingdom","code":"GB"},"coordinates":{"latitude":55.896572,"longitude":-3.644071}},"optimisedDate":"2018-10-15"},{"id":78668,"name":"Bath London Rd","key":"L-OMWKGH","type":"LEAF","parent":{"id":77903},"area":1911.2,"summer_temp":15.5,"winter_temp":15.5,"activity":"DEPARTMENT-STORE-FOOD","reference_devices":[{"device":{"id":425403},"type":"GAS"},{"device":{"id":433663},"type":"MAINSUPPLY"},{"device":{"id":434119},"type":"OUTDOORTEMP"}],"address":{"street":"London Road","zip":"BA1 6AE","city":"Bath","country":{"name":"United Kingdom","code":"GB"},"coordinates":{"latitude":51.39184,"longitude":-2.352605}},"optimisedDate":"2018-09-28"},{"id":78670,"name":"Beccles George Westwood Way","key":"L-8YQBIJ","type":"LEAF","parent":{"id":78000},"area":1970.94,"summer_temp":15.5,"winter_temp":15.5,"activity":"DEPARTMENT-STORE-FOOD","reference_devices":[{"device":{"id":424920},"type":"GAS"},{"device":{"id":433134},"type":"MAINSUPPLY"},{"device":{"id":434123},"type":"OUTDOORTEMP"}],"address":{"street":"George Westwood Way","zip":"NR34 9BJ","city":"Beccles","country":{"name":"United Kingdom","code":"GB"},"coordinates":{"latitude":52.46348,"longitude":1.568989}},"optimisedDate":"2018-09-16"},{"id":78671,"name":"Becontree Heath","key":"L-NFN5MZ","type":"LEAF","parent":{"id":77908},"area":2116.05,"summer_temp":15.5,"winter_temp":15.5,"activity":"DEPARTMENT-STORE-FOOD","reference_devices":[{"device":{"id":433122},"type":"MAINSUPPLY"},{"device":{"id":425393},"type":"GAS"}],"address":{"street":"Wood Lane, 481","zip":"RM8 3NT","city":"Dagenham","country":{"name":"United Kingdom","code":"GB"},"coordinates":{"latitude":51.559444,"longitude":0.148373}},"optimisedDate":"2018-08-16"},{"id":78672,"name":"Bedford","key":"L-WALFVY","type":"LEAF","parent":{"id":78000},"area":3713.99,"summer_temp":15.5,"winter_temp":15.5,"activity":"DEPARTMENT-STORE-FOOD","reference_devices":[],"address":{"street":"Ampthill Road","zip":"MK42 9JP","city":"Bedford","country":{"name":"United Kingdom","code":"GB"},"coordinates":{"latitude":52.12648,"longitude":-0.471102}}},{"id":78673,"name":"Bedlington","key":"L-DDMY1I","type":"LEAF","parent":{"id":78001},"area":719.16,"summer_temp":15.5,"winter_temp":15.5,"activity":"DEPARTMENT-STORE-FOOD","reference_devices":[{"device":{"id":433368},"type":"MAINSUPPLY"},{"device":{"id":434124},"type":"OUTDOORTEMP"},{"device":{"id":424969},"type":"GAS"}],"address":{"street":"Choppington Road","zip":"NE22 6LA","city":"Bedlington","country":{"name":"United Kingdom","code":"GB"},"coordinates":{"latitude":55.136177,"longitude":-1.59925}},"optimisedDate":"2018-09-30"},{"id":78674,"name":"Bellshill John St","key":"L-EYANNV","type":"LEAF","parent":{"id":78001},"area":1938.89,"summer_temp":15.5,"winter_temp":15.5,"activity":"DEPARTMENT-STORE-FOOD","reference_devices":[{"device":{"id":424965},"type":"GAS"},{"device":{"id":433507},"type":"MAINSUPPLY"}],"address":{"street":"John Street","zip":"ML4 1RJ","city":"Bellshill","country":{"name":"United Kingdom","code":"GB"},"coordinates":{"latitude":55.81824,"longitude":-4.021934}},"optimisedDate":"2018-10-16"},{"id":78675,"name":"Belper Chapel Street","key":"L-BLJFCX","type":"LEAF","parent":{"id":78000},"area":3466.96,"summer_temp":15.5,"winter_temp":15.5,"activity":"DEPARTMENT-STORE-FOOD","reference_devices":[{"device":{"id":433191},"type":"MAINSUPPLY"},{"device":{"id":424925},"type":"GAS"}],"address":{"street":"Chapel Street","zip":"DE56 1AR","city":"Belper","country":{"name":"United Kingdom","code":"GB"},"coordinates":{"latitude":53.021935,"longitude":-1.48447}},"optimisedDate":"2018-10-24"},{"id":78676,"name":"Berwick UT North Rd","key":"L-EJKKWI","type":"LEAF","parent":{"id":78001},"area":3207.01,"summer_temp":15.5,"winter_temp":15.5,"activity":"DEPARTMENT-STORE-FOOD","reference_devices":[{"device":{"id":433512},"type":"MAINSUPPLY"},{"device":{"id":434131},"type":"OUTDOORTEMP"},{"device":{"id":424912},"type":"GAS"}],"address":{"street":"North Road","zip":"TD15 1UQ","city":"Berwick Upon Tweed","country":{"name":"United Kingdom","code":"GB"},"coordinates":{"latitude":55.784225,"longitude":-2.014945}},"optimisedDate":"2018-09-24"},{"id":78677,"name":"Beverley","key":"L-RD7XJ6","type":"LEAF","parent":{"id":78000},"area":3296.39,"summer_temp":15.5,"winter_temp":15.5,"activity":"DEPARTMENT-STORE-FOOD","reference_devices":[{"device":{"id":424931},"type":"GAS"},{"device":{"id":433718},"type":"MAINSUPPLY"}],"address":{"street":"Victoria Road","zip":"HU17 8PJ","city":"Victoria Road","country":{"name":"United Kingdom","code":"GB"},"coordinates":{"latitude":53.826027,"longitude":-0.440409}},"optimisedDate":"2018-11-29"},{"id":78678,"name":"Bideford Kingsley Rd","key":"L-XJF1JA","type":"LEAF","parent":{"id":77903},"area":3304,"summer_temp":15.5,"winter_temp":15.5,"activity":"DEPARTMENT-STORE-FOOD","reference_devices":[{"device":{"id":434132},"type":"OUTDOORTEMP"},{"device":{"id":424972},"type":"GAS"},{"device":{"id":433659},"type":"MAINSUPPLY"}],"address":{"street":"Kingsley Road","zip":"EX39 2LG","city":"Bideford","country":{"name":"United Kingdom","code":"GB"},"coordinates":{"latitude":51.022484,"longitude":-4.208262}},"optimisedDate":"2018-10-12"},{"id":78679,"name":"Birmingham Small Heath","key":"L-YB1OOD","type":"LEAF","parent":{"id":78000},"area":3728.01,"summer_temp":15.5,"winter_temp":15.5,"activity":"DEPARTMENT-STORE-FOOD","reference_devices":[{"device":{"id":424978},"type":"GAS"},{"device":{"id":433289},"type":"MAINSUPPLY"}],"address":{"street":"Coventry Road, 280","zip":"B10 0XA","city":"Small Heath, Birmingham","country":{"name":"United Kingdom","code":"GB"},"coordinates":{"latitude":52.47395,"longitude":-1.865719}},"optimisedDate":"2018-10-28"},{"id":78680,"name":"Birtley","key":"L-NYMAYA","type":"LEAF","parent":{"id":78001},"area":2406.19,"summer_temp":15.5,"winter_temp":15.5,"activity":"DEPARTMENT-STORE-FOOD","reference_devices":[],"address":{"street":"Durham Road","zip":"DH3 2QH","city":"Birtley","country":{"name":"United Kingdom","code":"GB"},"coordinates":{"latitude":54.895256,"longitude":-1.577796}}},{"id":78681,"name":"Bishop Auckland","key":"L-MQGQQU","type":"LEAF","parent":{"id":78001},"area":3400.62,"summer_temp":15.5,"winter_temp":15.5,"activity":"DEPARTMENT-STORE-FOOD","reference_devices":[],"address":{"street":"Bob Hardisty Drive","zip":"DL14 7TH","city":"Bishop Auckland","country":{"name":"United Kingdom","code":"GB"},"coordinates":{"latitude":54.65902,"longitude":-1.6788}},"optimisedDate":"2018-11-15"},{"id":78682,"name":"Blackburn Railway Road","key":"L-F9J5PN","type":"LEAF","parent":{"id":78001},"area":3867.46,"summer_temp":15.5,"winter_temp":15.5,"activity":"DEPARTMENT-STORE-FOOD","reference_devices":[{"device":{"id":433407},"type":"MAINSUPPLY"},{"device":{"id":424950},"type":"GAS"}],"address":{"street":"Railway Road","zip":"BB1 5AX","city":"Blackburn","country":{"name":"United Kingdom","code":"GB"},"coordinates":{"latitude":53.747524,"longitude":-2.479956}},"optimisedDate":"2018-11-09"},{"id":78683,"name":"Blackpool Squires Gate","key":"L-SU4RWP","type":"LEAF","parent":{"id":78001},"area":3851.1,"summer_temp":15.5,"winter_temp":15.5,"activity":"DEPARTMENT-STORE-FOOD","reference_devices":[{"device":{"id":433405},"type":"MAINSUPPLY"},{"device":{"id":424982},"type":"GAS"}],"address":{"street":"Squires Gate Lane","zip":"FY4 2AY","city":"Blackpool","country":{"name":"United Kingdom","code":"GB"},"coordinates":{"latitude":53.78043,"longitude":-3.03485}},"optimisedDate":"2018-11-08"}]